maser/__main__.py
maser/__version__.py
maser/script.py
maser/setup_logging.py
maser4py-0.17.1.dist-info/LICENSE
maser4py-0.17.1.dist-info/METADATA
maser4py-0.17.1.dist-info/WHEEL
maser4py-0.17.1.dist-info/entry_points.txt
maser4py-0.17.1.dist-info/RECORD
