Metadata-Version: 2.3
Name: maser4py
Version: 0.17.1
Summary: maser4py offers tools to handle low frequency radioastronomy data
Home-page: https://pypi.org/project/maser4py
License: CECILL-B
Keywords: maser,data science,radioastronomy
Author: Baptiste CECCONI
Author-email: baptiste.cecconi@obspm.fr
Requires-Python: >=3.9,<4
Classifier: License :: CeCILL-B Free Software License Agreement (CECILL-B)
Classifier: Programming Language :: Python :: 3
Classifier: Programming Language :: Python :: 3.9
Classifier: Programming Language :: Python :: 3.10
Classifier: Programming Language :: Python :: 3.11
Classifier: Programming Language :: Python :: 3.12
Classifier: Programming Language :: Python :: 3.13
Provides-Extra: all
Provides-Extra: data
Provides-Extra: dev
Provides-Extra: jupyter
Provides-Extra: plot
Provides-Extra: tools
Requires-Dist: Sphinx (>=5.0.2,<6.0.0) ; extra == "dev"
Requires-Dist: black (>=22.6.0,<23.0.0) ; extra == "dev"
Requires-Dist: jupyter (>=1.0.0,<2.0.0) ; extra == "jupyter" or extra == "all"
Requires-Dist: jupytext (>=1.13.8,<2.0.0) ; extra == "jupyter" or extra == "all"
Requires-Dist: maser-data (>=0.5.1,<1.0) ; extra == "data" or extra == "plot" or extra == "all"
Requires-Dist: maser-plot (>=0.4.0,<1.0) ; extra == "plot" or extra == "all"
Requires-Dist: maser-tools (>=0.3.0,<1.0) ; extra == "tools" or extra == "all"
Requires-Dist: mypy (>=1.10,<2.0) ; extra == "dev"
Requires-Dist: myst-parser (>=0.18.0,<0.19.0) ; extra == "dev"
Requires-Dist: pre-commit (>=2.17.0,<3.0.0) ; extra == "dev"
Requires-Dist: pytest (>=7.0.1,<8.0.0) ; extra == "dev"
Requires-Dist: pytest-cov (>=3.0.0,<4.0.0) ; extra == "dev"
Requires-Dist: requests (>=2.27.1,<3.0.0) ; extra == "dev"
Requires-Dist: spacepy (>=0.4,<1.0) ; extra == "data" or extra == "plot" or extra == "tools" or extra == "all"
Requires-Dist: sphinx-rtd-theme (>=1.0.0,<2.0.0) ; extra == "dev"
Requires-Dist: tomli (>=2.0.1,<3.0.0) ; extra == "dev"
Project-URL: Documentation, https://maser.pages.obspm.fr/maser4py
Project-URL: Repository, https://github.com/maserlib/maser4py
Project-URL: Tracker, https://gitlab.obspm.fr/maser/maser4py/-/issues
